{"cameraMode":{"drawMode":0,"name":"Shaded","section":"Shading Mode"},"sceneLighting":false,"audioPlay":false,"sceneViewState":{"m_AlwaysRefresh":false,"showFog":true,"showSkybox":false,"showFlares":true,"showImageEffects":true,"showParticleSystems":true,"showVisualEffectGraphs":true,"m_FxEnabled":true},"in2DMode":false,"pivot":{"x":2.0,"y":0.75,"z":0.0},"rotation":{"x":0.06445279717445374,"y":0.009277277626097203,"z":-0.0005994658567942679,"w":0.9978796243667603},"size":1.6007640361785889,"orthographic":true}